{
    "urls_data": [
        {
            "url": null,
            "date": "April 13, 2026"
        },
        {
            "url": "https://daoinsights.com/news/subsidies-in-chinas-auto-market/",
            "date": "April 13, 2026"
        },
        {
            "url": "https://daoinsights.com/news/subsidies-in-chinas-auto-market/",
            "date": "April 13, 2026"
        },
        {
            "url": "https://daoinsights.com/news/winona/",
            "date": "April 13, 2026"
        }
    ]
}